pytda/__init__.py
pytda/auth.py
pytda/py.typed
pytda/streaming.py
pytda/api/__init__.py
pytda/api/client.py
pytda/api/method/__init__.py
pytda/api/method/base.py
pytda/api/method/get_option_chain.py
pytda/api/method/get_price_history.py
pytda/api/method/get_quote.py
pytda/api/method/get_quotes.py
pytda/api/method/get_user_principals.py
pytda-0.0.2.dist-info/LICENSE
pytda-0.0.2.dist-info/METADATA
pytda-0.0.2.dist-info/WHEEL
pytda-0.0.2.dist-info/top_level.txt
pytda-0.0.2.dist-info/RECORD
