Metadata-Version: 2.1
Name: pytda
Version: 0.0.2
Summary: Consume the TD Ameritrade API and Streaming Data
Author-email: Narvin Singh <Narvin.A.Singh@gmail.com>
License: The MIT License (MIT)
Project-URL: Homepage, https://gitlab.com/narvin/pytda
Project-URL: Repository, https://gitlab.com/narvin/pytda
Project-URL: Bug Tracker, https://gitlab.com/narvin/pytda/-/issues
Keywords: TD,TDA,TD Ameritrade,TD API
Classifier: Programming Language :: Python :: 3
Classifier: License :: OSI Approved :: MIT License
Classifier: Operating System :: OS Independent
Requires-Python: >=3.10
License-File: LICENSE
Requires-Dist: python-dateutil (>=2.8.2)
Requires-Dist: pytyu (>=0.0.5)
Requires-Dist: requests (>=2.27.1)
Requires-Dist: websockets (>=10.2)
Provides-Extra: code_quality
Requires-Dist: black (>=22.10.0) ; extra == 'code_quality'
Requires-Dist: mypy (>=0.991) ; extra == 'code_quality'
Requires-Dist: pylint (>=2.15.5) ; extra == 'code_quality'
Requires-Dist: pycodestyle (>=2.9.1) ; extra == 'code_quality'
Requires-Dist: types-python-dateutil (>=2.8.19) ; extra == 'code_quality'
Requires-Dist: types-requests (>=2.28.11.4) ; extra == 'code_quality'
Provides-Extra: deploy
Requires-Dist: build (>=0.7.0) ; extra == 'deploy'
Requires-Dist: twine (>=4.0.0) ; extra == 'deploy'
Provides-Extra: test
Requires-Dist: pytest (>=7.2.0) ; extra == 'test'
Requires-Dist: pytest-xdist (>=2.5.0) ; extra == 'test'
